LICENSE
MANIFEST.in
README.rst
setup.py
Flask_MongoAlchemy.egg-info/PKG-INFO
Flask_MongoAlchemy.egg-info/SOURCES.txt
Flask_MongoAlchemy.egg-info/dependency_links.txt
Flask_MongoAlchemy.egg-info/not-zip-safe
Flask_MongoAlchemy.egg-info/requires.txt
Flask_MongoAlchemy.egg-info/top_level.txt
flask_mongoalchemy/__init__.py
flask_mongoalchemy/meta.py