Metadata-Version: 1.1
Name: Flask-MongoAlchemy
Version: 0.7.1
Summary: Add Flask support for MongoDB using MongoAlchemy.
Home-page: http://github.com/cobrateam/flask-mongoalchemy
Author: Francisco Souza
Author-email: francisco@franciscosouza.net
License: BSD
Platform: any
Classifier: Environment :: Web Environment
Classifier: Intended Audience :: Developers
Classifier: License :: OSI Approved :: BSD License
Classifier: Operating System :: OS Independent
Classifier: Programming Language :: Python
Classifier: Topic :: Internet :: WWW/HTTP :: Dynamic Content
Classifier: Topic :: Software Development :: Libraries :: Python Modules
